bifrostapi/__init__.py
bifrostapi/components.py
bifrostapi/runs.py
bifrostapi/sample_components.py
bifrostapi/samples.py
bifrostapi/species.py
bifrostapi/utils.py
bifrostapi-0.1.1.dist-info/METADATA
bifrostapi-0.1.1.dist-info/WHEEL
bifrostapi-0.1.1.dist-info/top_level.txt
bifrostapi-0.1.1.dist-info/RECORD
