Metadata-Version: 2.1
Name: bifrostapi
Version: 0.1.1
Summary: Datahandling functions for bifrost dashboard
Home-page: https://github.com/ssi-dk/bifrostapi
Author: Martin Basterrechea
Author-email: mbas@ssi.dk
License: UNKNOWN
Platform: UNKNOWN
Requires-Python: >=3.6
Requires-Dist: pymongo
